{
    "validationErrorMap": {},
    "validationErrors": [],
    "outagesRegions": [
        {
            "id": "8498344828",
            "regionName": "Arvin",
            "numOutages": "1",
            "customersAffected": "4",
            "latitude": "34.98431",
            "longitude": "-118.89449",
            "outages": [
                {
                    "outageNumber": "2687307",
                    "outageStartTime": "1737346680",
                    "crewCurrentStatus": "PG&E is sending a repair crew to the outage location.",
                    "autoEtor": "1737360000",
                    "currentEtor": "1737403200",
                    "cause": "Our preliminary determination is that your outage was caused by an equipment issue.",
                    "estCustAffected": "4",
                    "lastUpdateTime": "1737356057",
                    "hazardFlag": "0",
                    "latitude": "34.98431",
                    "longitude": "-118.89449",
                    "outageDevices": [
                        {
                            "latitude": "34.97284",
                            "longitude": "-118.88616"
                        },
                        {
                            "latitude": "34.97288",
                            "longitude": "-118.88621"
                        },
                        {
                            "latitude": "34.97773",
                            "longitude": "-118.89265"
                        },
                        {
                            "latitude": "34.98271",
                            "longitude": "-118.89969"
                        },
                        {
                            "latitude": "34.97712",
                            "longitude": "-118.89247"
                        }
                    ]
                }
            ]
        },
        {
            "id": "8498344826",
            "regionName": "Berkeley",
            "numOutages": "1",
            "customersAffected": "17",
            "latitude": "37.86576",
            "longitude": "-122.26013",
            "outages": [
                {
                    "outageNumber": "2687310",
                    "outageStartTime": "1737352460",
                    "crewCurrentStatus": "PG&E repair crew is on-site working to restore power.",
                    "autoEtor": "1737381600",
                    "currentEtor": "1737381600",
                    "cause": "Our preliminary determination is that your outage was caused by scheduled maintenance work.",
                    "estCustAffected": "17",
                    "lastUpdateTime": "1737354913",
                    "hazardFlag": "0",
                    "latitude": "37.86576",
                    "longitude": "-122.26013"
                }
            ]
        },
        {
            "id": "8498344829",
            "regionName": "Foresthill",
            "numOutages": "2",
            "customersAffected": "120",
            "latitude": "38.99157",
            "longitude": "-120.86388",
            "outages": [
                {
                    "outageNumber": "2686735",
                    "outageStartTime": "1737216660",
                    "crewCurrentStatus": "PG&E repair crew is on-site working to restore power.",
                    "autoEtor": "1737230400",
                    "currentEtor": "1737230400",
                    "cause": "Our preliminary determination is that your outage was caused by scheduled maintenance work.",
                    "estCustAffected": "2",
                    "lastUpdateTime": "1737224530",
                    "hazardFlag": "0",
                    "latitude": "38.99157",
                    "longitude": "-120.86388"
                },
                {
                    "outageNumber": "2686897",
                    "outageStartTime": "1737232800",
                    "crewCurrentStatus": "PG&E has assigned a crew to assess the outage.",
                    "autoEtor": "1737243900",
                    "currentEtor": "1737243900",
                    "cause": "Unknown - PG&E will be assessing the cause.",
                    "estCustAffected": "118",
                    "lastUpdateTime": "1737236916",
                    "hazardFlag": "0",
                    "latitude": "38.99269",
                    "longitude": "-120.88287",
                    "outageDevices": [
                        {
                            "latitude": "38.97685",
                            "longitude": "-120.89391"
                        },
                        {
                            "latitude": "38.97714",
                            "longitude": "-120.88997"
                        },
                        {
                            "latitude": "38.97816",
                            "longitude": "-120.88866"
                        },
                        {
                            "latitude": "38.98461",
                            "longitude": "-120.88387"
                        },
                        {
                            "latitude": "38.98945",
                            "longitude": "-120.88046"
                        },
                        {
                            "latitude": "38.99266",
                            "longitude": "-120.88289"
                        },
                        {
                            "latitude": "38.9862",
                            "longitude": "-120.88746"
                        }
                    ]
                }
            ]
        },
        {
            "id": "8498344830",
            "regionName": "Fresno",
            "numOutages": "2",
            "customersAffected": "289",
            "latitude": "36.81538",
            "longitude": "-119.86184",
            "outages": [
                {
                    "outageNumber": "2687285",
                    "outageStartTime": "1737342502",
                    "crewCurrentStatus": "PG&E repair crew is on-site working to restore power.",
                    "autoEtor": "1737373500",
                    "currentEtor": "1737373500",
                    "cause": "Our preliminary determination is that your outage was caused by an equipment issue.",
                    "estCustAffected": "246",
                    "lastUpdateTime": "1737349721",
                    "hazardFlag": "0",
                    "latitude": "36.81538",
                    "longitude": "-119.86184",
                    "outageDevices": [
                        {
                            "latitude": "36.81228",
                            "longitude": "-119.85996"
                        },
                        {
                            "latitude": "36.81238",
                            "longitude": "-119.85979"
                        },
                        {
                            "latitude": "36.81282",
                            "longitude": "-119.85953"
                        },
                        {
                            "latitude": "36.81289",
                            "longitude": "-119.85952"
                        },
                        {
                            "latitude": "36.81329",
                            "longitude": "-119.85957"
                        },
                        {
                            "latitude": "36.81538",
                            "longitude": "-119.86215"
                        },
                        {
                            "latitude": "36.81261",
                            "longitude": "-119.86245"
                        },
                        {
                            "latitude": "36.81229",
                            "longitude": "-119.86135"
                        }
                    ]
                },
                {
                    "outageNumber": "2687275",
                    "outageStartTime": "1737339741",
                    "crewCurrentStatus": "PG&E repair crew is on-site working to restore power.",
                    "autoEtor": "1737371700",
                    "currentEtor": "1737371700",
                    "cause": "Our preliminary determination is that your outage was caused by an equipment issue.",
                    "estCustAffected": "43",
                    "lastUpdateTime": "1737348604",
                    "hazardFlag": "1",
                    "latitude": "36.81438",
                    "longitude": "-119.86249",
                    "outageDevices": [
                        {
                            "latitude": "36.81335",
                            "longitude": "-119.86541"
                        },
                        {
                            "latitude": "36.81352",
                            "longitude": "-119.86428"
                        },
                        {
                            "latitude": "36.81512",
                            "longitude": "-119.86365"
                        }
                    ]
                }
            ]
        },
        {
            "id": "8498344831",
            "regionName": "Kingsburg",
            "numOutages": "1",
            "customersAffected": "1",
            "latitude": "36.514",
            "longitude": "-119.54714",
            "outages": [
                {
                    "outageNumber": "2687229",
                    "outageStartTime": "1737328462",
                    "crewCurrentStatus": "PG&E is sending a repair crew to the outage location.",
                    "autoEtor": "1737340200",
                    "currentEtor": "1737374400",
                    "cause": "Our preliminary determination is that your outage was caused by an equipment issue.",
                    "estCustAffected": "1",
                    "lastUpdateTime": "1737346760",
                    "hazardFlag": "1",
                    "latitude": "36.514",
                    "longitude": "-119.54714"
                }
            ]
        },
        {
            "id": "8498344825",
            "regionName": "Lodi",
            "numOutages": "2",
            "customersAffected": "2",
            "latitude": "38.10821",
            "longitude": "-121.25739",
            "outages": [
                {
                    "outageNumber": "2687305",
                    "outageStartTime": "1737350364",
                    "crewCurrentStatus": "PG&E is unable to access the affected equipment.",
                    "autoEtor": "1737378900",
                    "currentEtor": "1737378900",
                    "cause": "Unknown - PG&E will be assessing the cause.",
                    "estCustAffected": "1",
                    "lastUpdateTime": "1737361066",
                    "hazardFlag": "0",
                    "latitude": "38.10821",
                    "longitude": "-121.25739"
                },
                {
                    "outageNumber": "2687306",
                    "outageStartTime": "1737350368",
                    "crewCurrentStatus": "PG&E is unable to access the affected equipment.",
                    "autoEtor": "1737378900",
                    "currentEtor": "1737378900",
                    "cause": "Unknown - PG&E will be assessing the cause.",
                    "estCustAffected": "1",
                    "lastUpdateTime": "1737361063",
                    "hazardFlag": "0",
                    "latitude": "38.10564",
                    "longitude": "-121.2598"
                }
            ]
        },
        {
            "id": "8498344822",
            "regionName": "Mc Farland",
            "numOutages": "1",
            "customersAffected": "13",
            "latitude": "35.71915",
            "longitude": "-119.32906",
            "outages": [
                {
                    "outageNumber": "2687323",
                    "outageStartTime": "1737356787",
                    "crewCurrentStatus": "PG&E is assessing the cause at the outage location.",
                    "autoEtor": "1737388800",
                    "currentEtor": "1737388800",
                    "cause": "PG&E is investigating the cause of your outage.",
                    "estCustAffected": "13",
                    "lastUpdateTime": "1737362043",
                    "hazardFlag": "0",
                    "latitude": "35.71915",
                    "longitude": "-119.32906"
                }
            ]
        },
        {
            "id": "8498344832",
            "regionName": "Nipinnawasee",
            "numOutages": "1",
            "customersAffected": "1",
            "latitude": "37.40209",
            "longitude": "-119.73311",
            "outages": [
                {
                    "outageNumber": "2687327",
                    "outageStartTime": "1737359637",
                    "crewEta": "1737363480",
                    "crewCurrentStatus": "PG&E is assessing the cause at the outage location.",
                    "autoEtor": "1737384300",
                    "currentEtor": "1737384300",
                    "cause": "PG&E is investigating the cause of your outage.",
                    "estCustAffected": "1",
                    "lastUpdateTime": "1737363363",
                    "hazardFlag": "0",
                    "latitude": "37.40209",
                    "longitude": "-119.73311"
                }
            ]
        },
        {
            "id": "8498344823",
            "regionName": "Oakland",
            "numOutages": "6",
            "customersAffected": "21",
            "latitude": "37.76457",
            "longitude": "-122.21003",
            "outages": [
                {
                    "outageNumber": "2687296",
                    "outageStartTime": "1737345620",
                    "crewCurrentStatus": "PG&E has assigned a crew to assess the outage.",
                    "autoEtor": "1737370800",
                    "currentEtor": "1737370800",
                    "cause": "Unknown - PG&E will be assessing the cause.",
                    "estCustAffected": "2",
                    "lastUpdateTime": "1737345928",
                    "hazardFlag": "0",
                    "latitude": "37.76457",
                    "longitude": "-122.21003"
                },
                {
                    "outageNumber": "2687329",
                    "outageStartTime": "1737363136",
                    "crewCurrentStatus": "PG&E has assigned a crew to assess the outage.",
                    "autoEtor": "1737383400",
                    "currentEtor": "1737383400",
                    "cause": "Unknown - PG&E will be assessing the cause.",
                    "estCustAffected": "1",
                    "lastUpdateTime": "1737363724",
                    "hazardFlag": "0",
                    "latitude": "37.83818",
                    "longitude": "-122.27454"
                },
                {
                    "outageNumber": "2687298",
                    "outageStartTime": "1737346302",
                    "crewCurrentStatus": "PG&E is unable to access the affected equipment.",
                    "autoEtor": "1737369000",
                    "currentEtor": "1737369000",
                    "cause": "Unknown - PG&E will be assessing the cause.",
                    "estCustAffected": "1",
                    "lastUpdateTime": "1737358291",
                    "hazardFlag": "0",
                    "latitude": "37.74053",
                    "longitude": "-122.203"
                },
                {
                    "outageNumber": "2687286",
                    "outageStartTime": "1737342931",
                    "crewCurrentStatus": "PG&E is unable to access the affected equipment.",
                    "autoEtor": "1737365400",
                    "currentEtor": "1737365400",
                    "cause": "Unknown - PG&E will be assessing the cause.",
                    "estCustAffected": "1",
                    "lastUpdateTime": "1737364535",
                    "hazardFlag": "0",
                    "latitude": "37.73962",
                    "longitude": "-122.20233"
                },
                {
                    "outageNumber": "2687290",
                    "outageStartTime": "1737343620",
                    "crewCurrentStatus": "PG&E is unable to access the affected equipment.",
                    "autoEtor": "1737356400",
                    "currentEtor": "1737388800",
                    "cause": "Unknown - PG&E will be assessing the cause.",
                    "estCustAffected": "1",
                    "lastUpdateTime": "1737362030",
                    "hazardFlag": "0",
                    "latitude": "37.79068",
                    "longitude": "-122.18392"
                },
                {
                    "outageNumber": "2687320",
                    "outageStartTime": "1737356088",
                    "crewCurrentStatus": "PG&E repair crew is on-site working to restore power.",
                    "cause": "Our preliminary determination is that your outage was caused by scheduled maintenance work.",
                    "estCustAffected": "15",
                    "lastUpdateTime": "1737357173",
                    "hazardFlag": "0",
                    "latitude": "37.76438",
                    "longitude": "-122.20959"
                }
            ]
        },
        {
            "id": "8498344827",
            "regionName": "San Francisco",
            "numOutages": "1",
            "customersAffected": "24",
            "latitude": "37.72246",
            "longitude": "-122.46455",
            "outages": [
                {
                    "outageNumber": "2687130",
                    "outageStartTime": "1737308345",
                    "crewCurrentStatus": "PG&E has assigned a crew to assess the outage.",
                    "autoEtor": "1737328500",
                    "currentEtor": "1737334800",
                    "cause": "Our preliminary determination is that your outage was caused by scheduled maintenance work.",
                    "estCustAffected": "24",
                    "lastUpdateTime": "1737334397",
                    "hazardFlag": "0",
                    "latitude": "37.72246",
                    "longitude": "-122.46455"
                }
            ]
        },
        {
            "id": "8498344824",
            "regionName": "San Jose",
            "numOutages": "4",
            "customersAffected": "145",
            "latitude": "37.29515",
            "longitude": "-121.85192",
            "outages": [
                {
                    "outageNumber": "2687326",
                    "outageStartTime": "1737357831",
                    "crewCurrentStatus": "PG&E has assigned a crew to assess the outage.",
                    "autoEtor": "1737375300",
                    "currentEtor": "1737375300",
                    "cause": "Unknown - PG&E will be assessing the cause.",
                    "estCustAffected": "1",
                    "lastUpdateTime": "1737357833",
                    "hazardFlag": "0",
                    "latitude": "37.29515",
                    "longitude": "-121.85192"
                },
                {
                    "outageNumber": "2687322",
                    "outageStartTime": "1737356244",
                    "crewCurrentStatus": "PG&E is assessing the cause at the outage location.",
                    "autoEtor": "1737372600",
                    "currentEtor": "1737372600",
                    "cause": "PG&E is investigating the cause of your outage.",
                    "estCustAffected": "137",
                    "lastUpdateTime": "1737360735",
                    "hazardFlag": "0",
                    "latitude": "37.30111",
                    "longitude": "-121.85848",
                    "outageDevices": [
                        {
                            "latitude": "37.2913",
                            "longitude": "-121.84952"
                        },
                        {
                            "latitude": "37.29143",
                            "longitude": "-121.84882"
                        },
                        {
                            "latitude": "37.29383",
                            "longitude": "-121.84857"
                        },
                        {
                            "latitude": "37.29455",
                            "longitude": "-121.84877"
                        },
                        {
                            "latitude": "37.3011",
                            "longitude": "-121.85825"
                        },
                        {
                            "latitude": "37.30143",
                            "longitude": "-121.85887"
                        },
                        {
                            "latitude": "37.2933",
                            "longitude": "-121.85678"
                        },
                        {
                            "latitude": "37.29147",
                            "longitude": "-121.85031"
                        }
                    ]
                },
                {
                    "outageNumber": "2687325",
                    "outageStartTime": "1737357143",
                    "crewCurrentStatus": "PG&E has assigned a crew to assess the outage.",
                    "autoEtor": "1737385200",
                    "currentEtor": "1737385200",
                    "cause": "Unknown - PG&E will be assessing the cause.",
                    "estCustAffected": "1",
                    "lastUpdateTime": "1737357149",
                    "hazardFlag": "0",
                    "latitude": "37.29107",
                    "longitude": "-121.84713"
                },
                {
                    "outageNumber": "2687172",
                    "outageStartTime": "1737315531",
                    "crewEta": "1737334560",
                    "crewCurrentStatus": "PG&E repair crew is on-site working to restore power.",
                    "autoEtor": "1737342900",
                    "currentEtor": "1737381600",
                    "cause": "Our preliminary determination is that your outage was caused by an equipment issue.",
                    "estCustAffected": "6",
                    "lastUpdateTime": "1737341436",
                    "hazardFlag": "0",
                    "latitude": "37.2573",
                    "longitude": "-121.85138"
                }
            ]
        },
        {
            "id": "8498344833",
            "regionName": "Soledad",
            "numOutages": "1",
            "customersAffected": "1",
            "latitude": "36.42322",
            "longitude": "-121.28627",
            "outages": [
                {
                    "outageNumber": "2687218",
                    "outageStartTime": "1737325794",
                    "crewCurrentStatus": "PG&E is sending a repair crew to the outage location.",
                    "autoEtor": "1737336600",
                    "currentEtor": "1737403200",
                    "cause": "Our preliminary determination is that your outage was caused by an equipment issue.",
                    "estCustAffected": "1",
                    "lastUpdateTime": "1737347401",
                    "hazardFlag": "1",
                    "latitude": "36.42322",
                    "longitude": "-121.28627"
                }
            ]
        }
    ],
    "isSuccess": true
}
