{
    "validationErrorMap": {},
    "validationErrors": [],
    "outagesRegions": [
        {
            "id": "5307142789",
            "regionName": "Atwater",
            "numOutages": "1",
            "customersAffected": "116",
            "latitude": "37.3312",
            "longitude": "-120.63459",
            "outages": [
                {
                    "outageNumber": "1853092",
                    "outageStartTime": "1667570460",
                    "crewCurrentStatus": "PG&E is assessing the cause at the outage location.",
                    "autoEtor": "1667582100",
                    "currentEtor": "1667582100",
                    "cause": "PG&E is investigating the cause of your outage.",
                    "estCustAffected": "116",
                    "lastUpdateTime": "1667574614",
                    "hazardFlag": "0",
                    "latitude": "37.3312",
                    "longitude": "-120.63459",
                    "outageDevices": [
                        {
                            "latitude": "37.30944",
                            "longitude": "-120.68583"
                        },
                        {
                            "latitude": "37.31045",
                            "longitude": "-120.67358"
                        },
                        {
                            "latitude": "37.312",
                            "longitude": "-120.65669"
                        },
                        {
                            "latitude": "37.3203",
                            "longitude": "-120.66399"
                        },
                        {
                            "latitude": "37.32398",
                            "longitude": "-120.6685"
                        },
                        {
                            "latitude": "37.32595",
                            "longitude": "-120.67389"
                        },
                        {
                            "latitude": "37.32913",
                            "longitude": "-120.6872"
                        },
                        {
                            "latitude": "37.32408",
                            "longitude": "-120.70274"
                        }
                    ]
                }
            ]
        },
        {
            "id": "5307142798",
            "regionName": "Auberry",
            "numOutages": "2",
            "customersAffected": "4",
            "latitude": "37.06705",
            "longitude": "-119.40726",
            "outages": [
                {
                    "outageNumber": "1853134",
                    "outageStartTime": "1667581200",
                    "crewCurrentStatus": "PG&E repair crew is on-site working to restore power.",
                    "currentEtor": "1667595600",
                    "cause": "Our preliminary determination is that your outage was caused by scheduled maintenance work.",
                    "estCustAffected": "0",
                    "lastUpdateTime": "1667574614",
                    "hazardFlag": "0",
                    "latitude": "37.06705",
                    "longitude": "-119.40726"
                },
                {
                    "outageNumber": "1853140",
                    "outageStartTime": "1667574720",
                    "crewCurrentStatus": "PG&E repair crew is on-site working to restore power.",
                    "currentEtor": "1667602800",
                    "cause": "Our preliminary determination is that your outage was caused by scheduled maintenance work.",
                    "estCustAffected": "4",
                    "lastUpdateTime": "1667574810",
                    "hazardFlag": "0",
                    "latitude": "37.06965",
                    "longitude": "-119.48052"
                }
            ]
        },
        {
            "id": "5307142809",
            "regionName": "Bakersfield",
            "numOutages": "7",
            "customersAffected": "39",
            "latitude": "35.29447",
            "longitude": "-119.00218",
            "outages": [
                {
                    "outageNumber": "1853131",
                    "outageStartTime": "1667574157",
                    "crewCurrentStatus": "PG&E repair crew is on-site working to restore power.",
                    "currentEtor": "1667584800",
                    "cause": "Our preliminary determination is that your outage was caused by scheduled maintenance work.",
                    "estCustAffected": "3",
                    "lastUpdateTime": "1667574474",
                    "hazardFlag": "0",
                    "latitude": "35.29447",
                    "longitude": "-119.00218"
                },
                {
                    "outageNumber": "1853060",
                    "outageStartTime": "1667558082",
                    "crewCurrentStatus": "PG&E is sending a repair crew to the outage location.",
                    "currentEtor": "1667584800",
                    "cause": "Our preliminary determination is that your outage was caused by an equipment issue.",
                    "estCustAffected": "0",
                    "lastUpdateTime": "1667570353",
                    "hazardFlag": "0",
                    "latitude": "35.312",
                    "longitude": "-118.84303"
                },
                {
                    "outageNumber": "1853083",
                    "outageStartTime": "1667567411",
                    "crewCurrentStatus": "PG&E is assessing the cause at the outage location.",
                    "autoEtor": "1667578500",
                    "currentEtor": "1667578500",
                    "cause": "PG&E is investigating the cause of your outage.",
                    "estCustAffected": "11",
                    "lastUpdateTime": "1667571921",
                    "hazardFlag": "1",
                    "latitude": "35.18003",
                    "longitude": "-119.1992",
                    "outageDevices": [
                        {
                            "latitude": "35.1519",
                            "longitude": "-119.20644"
                        },
                        {
                            "latitude": "35.15383",
                            "longitude": "-119.19936"
                        },
                        {
                            "latitude": "35.15389",
                            "longitude": "-119.19935"
                        },
                        {
                            "latitude": "35.15803",
                            "longitude": "-119.19909"
                        },
                        {
                            "latitude": "35.18001",
                            "longitude": "-119.19832"
                        },
                        {
                            "latitude": "35.17995",
                            "longitude": "-119.1992"
                        }
                    ]
                },
                {
                    "outageNumber": "1853081",
                    "outageStartTime": "1667558040",
                    "crewCurrentStatus": "PG&E has assigned a crew to assess the outage.",
                    "currentEtor": "1667584800",
                    "cause": "Unknown - PG&E will be assessing the cause.",
                    "estCustAffected": "1",
                    "lastUpdateTime": "1667570873",
                    "hazardFlag": "0",
                    "latitude": "35.31109",
                    "longitude": "-118.84302"
                },
                {
                    "outageNumber": "1853114",
                    "outageStartTime": "1667573082",
                    "crewCurrentStatus": "PG&E has assigned a crew to assess the outage.",
                    "autoEtor": "1667585700",
                    "currentEtor": "1667585700",
                    "cause": "Unknown - PG&E will be assessing the cause.",
                    "estCustAffected": "1",
                    "lastUpdateTime": "1667573082",
                    "hazardFlag": "0",
                    "latitude": "35.29488",
                    "longitude": "-119.06265"
                },
                {
                    "outageNumber": "1853106",
                    "outageStartTime": "1667572169",
                    "crewCurrentStatus": "PG&E assessment crew is en route to the outage.",
                    "autoEtor": "1667583000",
                    "currentEtor": "1667583000",
                    "cause": "Unknown - PG&E will be assessing the cause.",
                    "estCustAffected": "22",
                    "lastUpdateTime": "1667572295",
                    "hazardFlag": "0",
                    "latitude": "35.35829",
                    "longitude": "-118.98914"
                },
                {
                    "outageNumber": "1853099",
                    "outageStartTime": "1667571480",
                    "crewCurrentStatus": "PG&E has assigned a crew to assess the outage.",
                    "autoEtor": "1667583000",
                    "currentEtor": "1667583000",
                    "cause": "Unknown - PG&E will be assessing the cause.",
                    "estCustAffected": "1",
                    "lastUpdateTime": "1667571491",
                    "hazardFlag": "0",
                    "latitude": "35.34859",
                    "longitude": "-119.01483"
                }
            ]
        },
        {
            "id": "5307142780",
            "regionName": "Challenge",
            "numOutages": "1",
            "customersAffected": "1",
            "latitude": "39.48331",
            "longitude": "-121.22074",
            "outages": [
                {
                    "outageNumber": "1853112",
                    "outageStartTime": "1667576100",
                    "crewCurrentStatus": "PG&E repair crew is on-site working to restore power.",
                    "currentEtor": "1667601000",
                    "cause": "Our preliminary determination is that your outage was caused by scheduled maintenance work.",
                    "estCustAffected": "1",
                    "lastUpdateTime": "1667574285",
                    "hazardFlag": "0",
                    "latitude": "39.48331",
                    "longitude": "-121.22074"
                }
            ]
        },
        {
            "id": "5307142775",
            "regionName": "Clearlake",
            "numOutages": "1",
            "customersAffected": "7",
            "latitude": "38.9373",
            "longitude": "-122.60851",
            "outages": [
                {
                    "outageNumber": "1853122",
                    "outageStartTime": "1667574120",
                    "crewCurrentStatus": "PG&E repair crew is on-site working to restore power.",
                    "currentEtor": "1667595600",
                    "cause": "Our preliminary determination is that your outage was caused by scheduled maintenance work.",
                    "estCustAffected": "7",
                    "lastUpdateTime": "1667574449",
                    "hazardFlag": "0",
                    "latitude": "38.9373",
                    "longitude": "-122.60851",
                    "outageDevices": [
                        {
                            "latitude": "38.93731",
                            "longitude": "-122.60774"
                        },
                        {
                            "latitude": "38.93731",
                            "longitude": "-122.6072"
                        },
                        {
                            "latitude": "38.93795",
                            "longitude": "-122.60756"
                        },
                        {
                            "latitude": "38.93734",
                            "longitude": "-122.60829"
                        }
                    ]
                }
            ]
        },
        {
            "id": "5307142810",
            "regionName": "Colusa",
            "numOutages": "1",
            "customersAffected": "9",
            "latitude": "39.24684",
            "longitude": "-122.08473",
            "outages": [
                {
                    "outageNumber": "1853090",
                    "outageStartTime": "1667570713",
                    "crewCurrentStatus": "PG&E assessment crew is en route to the outage.",
                    "autoEtor": "1667583900",
                    "currentEtor": "1667583900",
                    "cause": "Unknown - PG&E will be assessing the cause.",
                    "estCustAffected": "9",
                    "lastUpdateTime": "1667570719",
                    "hazardFlag": "0",
                    "latitude": "39.24684",
                    "longitude": "-122.08473",
                    "outageDevices": [
                        {
                            "latitude": "39.24645",
                            "longitude": "-122.0908"
                        },
                        {
                            "latitude": "39.24686",
                            "longitude": "-122.09093"
                        },
                        {
                            "latitude": "39.26133",
                            "longitude": "-122.09581"
                        },
                        {
                            "latitude": "39.26153",
                            "longitude": "-122.09641"
                        },
                        {
                            "latitude": "39.26168",
                            "longitude": "-122.11518"
                        }
                    ]
                }
            ]
        },
        {
            "id": "5307142781",
            "regionName": "Durham",
            "numOutages": "1",
            "customersAffected": "4",
            "latitude": "39.69828",
            "longitude": "-121.79522",
            "outages": [
                {
                    "outageNumber": "1853105",
                    "outageStartTime": "1667572015",
                    "crewCurrentStatus": "PG&E assessment crew is en route to the outage.",
                    "autoEtor": "1667583900",
                    "currentEtor": "1667583900",
                    "cause": "PG&E is investigating the cause of your outage.",
                    "estCustAffected": "4",
                    "lastUpdateTime": "1667574336",
                    "hazardFlag": "0",
                    "latitude": "39.69828",
                    "longitude": "-121.79522"
                }
            ]
        },
        {
            "id": "5307142776",
            "regionName": "El Sobrante",
            "numOutages": "1",
            "customersAffected": "1",
            "latitude": "37.96653",
            "longitude": "-122.3063",
            "outages": [
                {
                    "outageNumber": "1853079",
                    "outageStartTime": "1667566813",
                    "crewCurrentStatus": "PG&E has assigned a crew to assess the outage.",
                    "autoEtor": "1667579400",
                    "currentEtor": "1667579400",
                    "cause": "Unknown - PG&E will be assessing the cause.",
                    "estCustAffected": "1",
                    "lastUpdateTime": "1667567095",
                    "hazardFlag": "0",
                    "latitude": "37.96653",
                    "longitude": "-122.3063"
                }
            ]
        },
        {
            "id": "5307142814",
            "regionName": "Fort Bragg",
            "numOutages": "1",
            "customersAffected": "1",
            "latitude": "39.40538",
            "longitude": "-123.724",
            "outages": [
                {
                    "outageNumber": "1853115",
                    "outageStartTime": "1667574000",
                    "crewCurrentStatus": "PG&E repair crew is on-site working to restore power.",
                    "currentEtor": "1667588400",
                    "cause": "Our preliminary determination is that your outage was caused by scheduled maintenance work.",
                    "estCustAffected": "1",
                    "lastUpdateTime": "1667574285",
                    "hazardFlag": "0",
                    "latitude": "39.40538",
                    "longitude": "-123.724"
                }
            ]
        },
        {
            "id": "5307142799",
            "regionName": "Fresno",
            "numOutages": "1",
            "customersAffected": "1",
            "latitude": "36.78543",
            "longitude": "-119.84362",
            "outages": [
                {
                    "outageNumber": "1853108",
                    "outageStartTime": "1667572200",
                    "crewCurrentStatus": "PG&E has assigned a crew to assess the outage.",
                    "autoEtor": "1667583000",
                    "currentEtor": "1667583000",
                    "cause": "Unknown - PG&E will be assessing the cause.",
                    "estCustAffected": "1",
                    "lastUpdateTime": "1667573348",
                    "hazardFlag": "0",
                    "latitude": "36.78543",
                    "longitude": "-119.84362"
                }
            ]
        },
        {
            "id": "5307142782",
            "regionName": "Gilroy",
            "numOutages": "2",
            "customersAffected": "356",
            "latitude": "37.05924",
            "longitude": "-121.54854",
            "outages": [
                {
                    "outageNumber": "1853130",
                    "outageStartTime": "1667574458",
                    "crewCurrentStatus": "PG&E has assigned a crew to assess the outage.",
                    "autoEtor": "1667586600",
                    "currentEtor": "1667586600",
                    "cause": "Unknown - PG&E will be assessing the cause.",
                    "estCustAffected": "1",
                    "lastUpdateTime": "1667574462",
                    "hazardFlag": "0",
                    "latitude": "37.05924",
                    "longitude": "-121.54854"
                },
                {
                    "outageNumber": "1853085",
                    "outageStartTime": "1667568360",
                    "crewCurrentStatus": "PG&E is assessing the cause at the outage location.",
                    "autoEtor": "1667582100",
                    "currentEtor": "1667582100",
                    "cause": "PG&E is investigating the cause of your outage.",
                    "estCustAffected": "355",
                    "lastUpdateTime": "1667574724",
                    "hazardFlag": "3",
                    "latitude": "37.01633",
                    "longitude": "-121.54463",
                    "outageDevices": [
                        {
                            "latitude": "36.99768",
                            "longitude": "-121.51143"
                        },
                        {
                            "latitude": "37.03325",
                            "longitude": "-121.42672"
                        },
                        {
                            "latitude": "37.03648",
                            "longitude": "-121.422"
                        },
                        {
                            "latitude": "37.11916",
                            "longitude": "-121.54832"
                        },
                        {
                            "latitude": "37.09735",
                            "longitude": "-121.54542"
                        },
                        {
                            "latitude": "37.03649",
                            "longitude": "-121.53024"
                        },
                        {
                            "latitude": "37.02527",
                            "longitude": "-121.52576"
                        },
                        {
                            "latitude": "37.00008",
                            "longitude": "-121.51292"
                        }
                    ]
                }
            ]
        },
        {
            "id": "5307142815",
            "regionName": "Grass Valley",
            "numOutages": "1",
            "customersAffected": "3",
            "latitude": "39.14519",
            "longitude": "-120.98119",
            "outages": [
                {
                    "outageNumber": "1853141",
                    "outageStartTime": "1667577600",
                    "crewCurrentStatus": "PG&E repair crew is on-site working to restore power.",
                    "currentEtor": "1667597400",
                    "cause": "Our preliminary determination is that your outage was caused by scheduled maintenance work.",
                    "estCustAffected": "3",
                    "lastUpdateTime": "1667574791",
                    "hazardFlag": "0",
                    "latitude": "39.14519",
                    "longitude": "-120.98119"
                }
            ]
        },
        {
            "id": "5307142816",
            "regionName": "Hollister",
            "numOutages": "2",
            "customersAffected": "2",
            "latitude": "36.83931",
            "longitude": "-121.40599",
            "outages": [
                {
                    "outageNumber": "1853132",
                    "outageStartTime": "1667574439",
                    "crewCurrentStatus": "PG&E repair crew is on-site working to restore power.",
                    "currentEtor": "1667601000",
                    "cause": "Our preliminary determination is that your outage was caused by scheduled maintenance work.",
                    "estCustAffected": "1",
                    "lastUpdateTime": "1667574558",
                    "hazardFlag": "0",
                    "latitude": "36.83931",
                    "longitude": "-121.40599"
                },
                {
                    "outageNumber": "1853139",
                    "outageStartTime": "1667574676",
                    "crewCurrentStatus": "PG&E has assigned a crew to assess the outage.",
                    "autoEtor": "1667600100",
                    "currentEtor": "1667600100",
                    "cause": "Unknown - PG&E will be assessing the cause.",
                    "estCustAffected": "1",
                    "lastUpdateTime": "1667574686",
                    "hazardFlag": "0",
                    "latitude": "36.84705",
                    "longitude": "-121.30296"
                }
            ]
        },
        {
            "id": "5307142811",
            "regionName": "Kensington",
            "numOutages": "1",
            "customersAffected": "9",
            "latitude": "37.9017",
            "longitude": "-122.28144",
            "outages": [
                {
                    "outageNumber": "1853143",
                    "outageStartTime": "1667574501",
                    "crewCurrentStatus": "PG&E repair crew is on-site working to restore power.",
                    "currentEtor": "1667595600",
                    "cause": "Our preliminary determination is that your outage was caused by scheduled maintenance work.",
                    "estCustAffected": "9",
                    "lastUpdateTime": "1667574811",
                    "hazardFlag": "0",
                    "latitude": "37.9017",
                    "longitude": "-122.28144"
                }
            ]
        },
        {
            "id": "5307142792",
            "regionName": "La Grange",
            "numOutages": "2",
            "customersAffected": "2",
            "latitude": "37.72108",
            "longitude": "-120.34527",
            "outages": [
                {
                    "outageNumber": "1853137",
                    "outageStartTime": "1667574318",
                    "crewCurrentStatus": "PG&E repair crew is on-site working to restore power.",
                    "currentEtor": "1667602800",
                    "cause": "Our preliminary determination is that your outage was caused by scheduled maintenance work.",
                    "estCustAffected": "1",
                    "lastUpdateTime": "1667574630",
                    "hazardFlag": "0",
                    "latitude": "37.72108",
                    "longitude": "-120.34527"
                },
                {
                    "outageNumber": "1853142",
                    "outageStartTime": "1667574478",
                    "crewCurrentStatus": "PG&E has assigned a crew to assess the outage.",
                    "currentEtor": "1667602800",
                    "cause": "Our preliminary determination is that your outage was caused by scheduled maintenance work.",
                    "estCustAffected": "1",
                    "lastUpdateTime": "1667574794",
                    "hazardFlag": "0",
                    "latitude": "37.70487",
                    "longitude": "-120.34386"
                }
            ]
        },
        {
            "id": "5307142777",
            "regionName": "Linda",
            "numOutages": "1",
            "customersAffected": "2",
            "latitude": "39.13123",
            "longitude": "-121.55973",
            "outages": [
                {
                    "outageNumber": "1853118",
                    "outageStartTime": "1667574060",
                    "crewCurrentStatus": "PG&E repair crew is on-site working to restore power.",
                    "currentEtor": "1667593800",
                    "cause": "Our preliminary determination is that your outage was caused by scheduled maintenance work.",
                    "estCustAffected": "2",
                    "lastUpdateTime": "1667574349",
                    "hazardFlag": "0",
                    "latitude": "39.13123",
                    "longitude": "-121.55973"
                }
            ]
        },
        {
            "id": "5307142800",
            "regionName": "Livermore",
            "numOutages": "1",
            "customersAffected": "7",
            "latitude": "37.67684",
            "longitude": "-121.75706",
            "outages": [
                {
                    "outageNumber": "1853116",
                    "outageStartTime": "1667573821",
                    "crewCurrentStatus": "PG&E has assigned a crew to assess the outage.",
                    "autoEtor": "1667594700",
                    "currentEtor": "1667594700",
                    "cause": "Unknown - PG&E will be assessing the cause.",
                    "estCustAffected": "7",
                    "lastUpdateTime": "1667574344",
                    "hazardFlag": "0",
                    "latitude": "37.67684",
                    "longitude": "-121.75706"
                }
            ]
        },
        {
            "id": "5307142805",
            "regionName": "Lodoga",
            "numOutages": "1",
            "customersAffected": "130",
            "latitude": "39.30106",
            "longitude": "-122.49413",
            "outages": [
                {
                    "outageNumber": "1853066",
                    "outageStartTime": "1667559360",
                    "crewCurrentStatus": "PG&E is assessing the cause at the outage location.",
                    "autoEtor": "1667577600",
                    "currentEtor": "1667577600",
                    "cause": "PG&E is investigating the cause of your outage.",
                    "estCustAffected": "130",
                    "lastUpdateTime": "1667567391",
                    "hazardFlag": "0",
                    "latitude": "39.30106",
                    "longitude": "-122.49413",
                    "outageDevices": [
                        {
                            "latitude": "39.15281",
                            "longitude": "-122.43881"
                        },
                        {
                            "latitude": "39.19013",
                            "longitude": "-122.42109"
                        },
                        {
                            "latitude": "39.19552",
                            "longitude": "-122.42048"
                        },
                        {
                            "latitude": "39.35145",
                            "longitude": "-122.45674"
                        },
                        {
                            "latitude": "39.36597",
                            "longitude": "-122.4689"
                        },
                        {
                            "latitude": "39.3114",
                            "longitude": "-122.50852"
                        },
                        {
                            "latitude": "39.30442",
                            "longitude": "-122.51023"
                        },
                        {
                            "latitude": "39.16344",
                            "longitude": "-122.48213"
                        }
                    ]
                }
            ]
        },
        {
            "id": "5307142793",
            "regionName": "Lucas Valley-Marinwood",
            "numOutages": "1",
            "customersAffected": "1",
            "latitude": "38.02713",
            "longitude": "-122.56931",
            "outages": [
                {
                    "outageNumber": "1853098",
                    "outageStartTime": "1667571361",
                    "crewCurrentStatus": "PG&E is assessing the cause at the outage location.",
                    "autoEtor": "1667584800",
                    "currentEtor": "1667584800",
                    "cause": "PG&E is investigating the cause of your outage.",
                    "estCustAffected": "1",
                    "lastUpdateTime": "1667573848",
                    "hazardFlag": "0",
                    "latitude": "38.02713",
                    "longitude": "-122.56931"
                }
            ]
        },
        {
            "id": "5307142817",
            "regionName": "Madera",
            "numOutages": "2",
            "customersAffected": "68",
            "latitude": "36.95645",
            "longitude": "-120.0943",
            "outages": [
                {
                    "outageNumber": "1853121",
                    "outageStartTime": "1667574144",
                    "crewCurrentStatus": "PG&E repair crew is on-site working to restore power.",
                    "currentEtor": "1667601000",
                    "cause": "Our preliminary determination is that your outage was caused by scheduled maintenance work.",
                    "estCustAffected": "50",
                    "lastUpdateTime": "1667574689",
                    "hazardFlag": "0",
                    "latitude": "36.95645",
                    "longitude": "-120.0943",
                    "outageDevices": [
                        {
                            "latitude": "36.95673",
                            "longitude": "-120.09346"
                        },
                        {
                            "latitude": "36.95765",
                            "longitude": "-120.09499"
                        },
                        {
                            "latitude": "36.95758",
                            "longitude": "-120.09619"
                        },
                        {
                            "latitude": "36.95677",
                            "longitude": "-120.09512"
                        }
                    ]
                },
                {
                    "outageNumber": "1853126",
                    "outageStartTime": "1667574325",
                    "crewCurrentStatus": "PG&E repair crew is on-site working to restore power.",
                    "currentEtor": "1667599680",
                    "cause": "Our preliminary determination is that your outage was caused by scheduled maintenance work.",
                    "estCustAffected": "18",
                    "lastUpdateTime": "1667574528",
                    "hazardFlag": "0",
                    "latitude": "36.95637",
                    "longitude": "-120.09227",
                    "outageDevices": [
                        {
                            "latitude": "36.95638",
                            "longitude": "-120.09251"
                        },
                        {
                            "latitude": "36.95639",
                            "longitude": "-120.09311"
                        },
                        {
                            "latitude": "36.9564",
                            "longitude": "-120.09517"
                        },
                        {
                            "latitude": "36.9564",
                            "longitude": "-120.0962"
                        },
                        {
                            "latitude": "36.95639",
                            "longitude": "-120.09465"
                        }
                    ]
                }
            ]
        },
        {
            "id": "5307142783",
            "regionName": "Mariposa",
            "numOutages": "2",
            "customersAffected": "10",
            "latitude": "37.44764",
            "longitude": "-119.84408",
            "outages": [
                {
                    "outageNumber": "1853073",
                    "outageStartTime": "1667574000",
                    "crewCurrentStatus": "PG&E repair crew is on-site working to restore power.",
                    "currentEtor": "1667602800",
                    "cause": "Our preliminary determination is that your outage was caused by scheduled maintenance work.",
                    "estCustAffected": "8",
                    "lastUpdateTime": "1667567080",
                    "hazardFlag": "0",
                    "latitude": "37.44764",
                    "longitude": "-119.84408",
                    "outageDevices": [
                        {
                            "latitude": "37.44198",
                            "longitude": "-119.8411"
                        },
                        {
                            "latitude": "37.44664",
                            "longitude": "-119.84457"
                        },
                        {
                            "latitude": "37.44452",
                            "longitude": "-119.84693"
                        },
                        {
                            "latitude": "37.44376",
                            "longitude": "-119.84643"
                        }
                    ]
                },
                {
                    "outageNumber": "1853146",
                    "outageStartTime": "1667574539",
                    "crewCurrentStatus": "PG&E has assigned a crew to assess the outage.",
                    "currentEtor": "1667592000",
                    "cause": "Our preliminary determination is that your outage was caused by scheduled maintenance work.",
                    "estCustAffected": "2",
                    "lastUpdateTime": "1667574853",
                    "hazardFlag": "0",
                    "latitude": "37.47405",
                    "longitude": "-119.7337"
                }
            ]
        },
        {
            "id": "5307142794",
            "regionName": "Moss Landing",
            "numOutages": "1",
            "customersAffected": "6",
            "latitude": "36.82874",
            "longitude": "-121.78003",
            "outages": [
                {
                    "outageNumber": "1852801",
                    "outageStartTime": "1667513398",
                    "crewCurrentStatus": "PG&E repair crew is en route to the outage location.",
                    "currentEtor": "1667588400",
                    "cause": "Our preliminary determination is that your outage was caused by an equipment issue.",
                    "estCustAffected": "6",
                    "lastUpdateTime": "1667527501",
                    "hazardFlag": "0",
                    "latitude": "36.82874",
                    "longitude": "-121.78003"
                }
            ]
        },
        {
            "id": "5307142790",
            "regionName": "Nevada City",
            "numOutages": "1",
            "customersAffected": "8",
            "latitude": "39.24952",
            "longitude": "-121.12712",
            "outages": [
                {
                    "outageNumber": "1853136",
                    "outageStartTime": "1667574420",
                    "crewCurrentStatus": "PG&E repair crew is on-site working to restore power.",
                    "currentEtor": "1667602800",
                    "cause": "Our preliminary determination is that your outage was caused by scheduled maintenance work.",
                    "estCustAffected": "8",
                    "lastUpdateTime": "1667574791",
                    "hazardFlag": "0",
                    "latitude": "39.24952",
                    "longitude": "-121.12712",
                    "outageDevices": [
                        {
                            "latitude": "39.24727",
                            "longitude": "-121.12625"
                        },
                        {
                            "latitude": "39.24815",
                            "longitude": "-121.11877"
                        },
                        {
                            "latitude": "39.2495",
                            "longitude": "-121.12641"
                        }
                    ]
                }
            ]
        },
        {
            "id": "5307142784",
            "regionName": "Nipomo",
            "numOutages": "1",
            "customersAffected": "1",
            "latitude": "35.00488",
            "longitude": "-120.53974",
            "outages": [
                {
                    "outageNumber": "1853129",
                    "outageStartTime": "1667574427",
                    "crewCurrentStatus": "PG&E assessment crew is en route to the outage.",
                    "autoEtor": "1667585700",
                    "currentEtor": "1667585700",
                    "cause": "Unknown - PG&E will be assessing the cause.",
                    "estCustAffected": "1",
                    "lastUpdateTime": "1667574431",
                    "hazardFlag": "1",
                    "latitude": "35.00488",
                    "longitude": "-120.53974"
                }
            ]
        },
        {
            "id": "5307142801",
            "regionName": "North Richmond",
            "numOutages": "1",
            "customersAffected": "1",
            "latitude": "37.96828",
            "longitude": "-122.36196",
            "outages": [
                {
                    "outageNumber": "1853103",
                    "outageStartTime": "1667571776",
                    "crewCurrentStatus": "PG&E is assessing the cause at the outage location.",
                    "autoEtor": "1667583900",
                    "currentEtor": "1667583900",
                    "cause": "PG&E is investigating the cause of your outage.",
                    "estCustAffected": "1",
                    "lastUpdateTime": "1667572561",
                    "hazardFlag": "1",
                    "latitude": "37.96828",
                    "longitude": "-122.36196"
                }
            ]
        },
        {
            "id": "5307142812",
            "regionName": "Novato",
            "numOutages": "1",
            "customersAffected": "316",
            "latitude": "38.10378",
            "longitude": "-122.60689",
            "outages": [
                {
                    "outageNumber": "1853124",
                    "outageStartTime": "1667574421",
                    "crewCurrentStatus": "PG&E has assigned a crew to assess the outage.",
                    "autoEtor": "1667589300",
                    "currentEtor": "1667589300",
                    "cause": "Unknown - PG&E will be assessing the cause.",
                    "estCustAffected": "316",
                    "lastUpdateTime": "1667574942",
                    "hazardFlag": "0",
                    "latitude": "38.10378",
                    "longitude": "-122.60689",
                    "outageDevices": [
                        {
                            "latitude": "38.09346",
                            "longitude": "-122.61257"
                        },
                        {
                            "latitude": "38.09401",
                            "longitude": "-122.60912"
                        },
                        {
                            "latitude": "38.10336",
                            "longitude": "-122.60701"
                        },
                        {
                            "latitude": "38.10235",
                            "longitude": "-122.61284"
                        },
                        {
                            "latitude": "38.1019",
                            "longitude": "-122.61403"
                        },
                        {
                            "latitude": "38.09412",
                            "longitude": "-122.61354"
                        }
                    ]
                }
            ]
        },
        {
            "id": "5307142785",
            "regionName": "Oakdale",
            "numOutages": "1",
            "customersAffected": "4",
            "latitude": "37.74009",
            "longitude": "-120.80224",
            "outages": [
                {
                    "outageNumber": "1851406",
                    "outageStartTime": "1667415600",
                    "crewCurrentStatus": "PG&E has assigned a crew to assess the outage.",
                    "cause": "Our preliminary determination is that your outage was caused by the weather.",
                    "estCustAffected": "4",
                    "lastUpdateTime": "1667499279",
                    "hazardFlag": "0",
                    "latitude": "37.74009",
                    "longitude": "-120.80224",
                    "outageDevices": [
                        {
                            "latitude": "37.74431",
                            "longitude": "-120.80382"
                        },
                        {
                            "latitude": "37.74582",
                            "longitude": "-120.80162"
                        },
                        {
                            "latitude": "37.74727",
                            "longitude": "-120.79952"
                        },
                        {
                            "latitude": "37.74993",
                            "longitude": "-120.80141"
                        }
                    ]
                }
            ]
        },
        {
            "id": "5307142818",
            "regionName": "Orland",
            "numOutages": "1",
            "customersAffected": "1",
            "latitude": "39.75132",
            "longitude": "-122.19028",
            "outages": [
                {
                    "outageNumber": "1853097",
                    "outageStartTime": "1667571116",
                    "crewCurrentStatus": "PG&E has assigned a crew to assess the outage.",
                    "autoEtor": "1667582100",
                    "currentEtor": "1667582100",
                    "cause": "Unknown - PG&E will be assessing the cause.",
                    "estCustAffected": "1",
                    "lastUpdateTime": "1667571120",
                    "hazardFlag": "1",
                    "latitude": "39.75132",
                    "longitude": "-122.19028"
                }
            ]
        },
        {
            "id": "5307142795",
            "regionName": "Palermo",
            "numOutages": "1",
            "customersAffected": "3",
            "latitude": "39.41907",
            "longitude": "-121.5092",
            "outages": [
                {
                    "outageNumber": "1853150",
                    "outageStartTime": "1667574586",
                    "crewCurrentStatus": "PG&E repair crew is on-site working to restore power.",
                    "currentEtor": "1667602800",
                    "cause": "Our preliminary determination is that your outage was caused by scheduled maintenance work.",
                    "estCustAffected": "3",
                    "lastUpdateTime": "1667574901",
                    "hazardFlag": "0",
                    "latitude": "39.41907",
                    "longitude": "-121.5092",
                    "outageDevices": [
                        {
                            "latitude": "39.41979",
                            "longitude": "-121.50856"
                        },
                        {
                            "latitude": "39.42027",
                            "longitude": "-121.50712"
                        },
                        {
                            "latitude": "39.42063",
                            "longitude": "-121.50679"
                        }
                    ]
                }
            ]
        },
        {
            "id": "5307142778",
            "regionName": "Paradise",
            "numOutages": "1",
            "customersAffected": "3",
            "latitude": "39.75759",
            "longitude": "-121.62303",
            "outages": [
                {
                    "outageNumber": "1853133",
                    "outageStartTime": "1667574300",
                    "crewCurrentStatus": "PG&E repair crew is on-site working to restore power.",
                    "currentEtor": "1667602800",
                    "cause": "Our preliminary determination is that your outage was caused by scheduled maintenance work.",
                    "estCustAffected": "3",
                    "lastUpdateTime": "1667574513",
                    "hazardFlag": "0",
                    "latitude": "39.75759",
                    "longitude": "-121.62303"
                }
            ]
        },
        {
            "id": "5307142796",
            "regionName": "Pine Grove",
            "numOutages": "1",
            "customersAffected": "691",
            "latitude": "38.41509",
            "longitude": "-120.68528",
            "outages": [
                {
                    "outageNumber": "1852868",
                    "outageStartTime": "1667519640",
                    "crewCurrentStatus": "PG&E is assessing the cause at the outage location.",
                    "currentEtor": "1667592000",
                    "cause": "PG&E is investigating the cause of your outage.",
                    "estCustAffected": "691",
                    "lastUpdateTime": "1667571427",
                    "hazardFlag": "2",
                    "latitude": "38.41509",
                    "longitude": "-120.68528",
                    "outageDevices": [
                        {
                            "latitude": "38.37285",
                            "longitude": "-120.7599"
                        },
                        {
                            "latitude": "38.3772",
                            "longitude": "-120.74317"
                        },
                        {
                            "latitude": "38.38565",
                            "longitude": "-120.72208"
                        },
                        {
                            "latitude": "38.39415",
                            "longitude": "-120.70207"
                        },
                        {
                            "latitude": "38.4111",
                            "longitude": "-120.68471"
                        },
                        {
                            "latitude": "38.4195",
                            "longitude": "-120.6842"
                        },
                        {
                            "latitude": "38.42263",
                            "longitude": "-120.68409"
                        },
                        {
                            "latitude": "38.43656",
                            "longitude": "-120.6846"
                        },
                        {
                            "latitude": "38.43769",
                            "longitude": "-120.68675"
                        },
                        {
                            "latitude": "38.42487",
                            "longitude": "-120.71674"
                        },
                        {
                            "latitude": "38.39876",
                            "longitude": "-120.74268"
                        },
                        {
                            "latitude": "38.38138",
                            "longitude": "-120.75938"
                        },
                        {
                            "latitude": "38.37775",
                            "longitude": "-120.76159"
                        },
                        {
                            "latitude": "38.37482",
                            "longitude": "-120.76106"
                        }
                    ]
                }
            ]
        },
        {
            "id": "5307142806",
            "regionName": "Planada",
            "numOutages": "1",
            "customersAffected": "1",
            "latitude": "37.2844",
            "longitude": "-120.32113",
            "outages": [
                {
                    "outageNumber": "1853127",
                    "outageStartTime": "1667574360",
                    "crewCurrentStatus": "PG&E assessment crew is en route to the outage.",
                    "autoEtor": "1667584800",
                    "currentEtor": "1667584800",
                    "cause": "Unknown - PG&E will be assessing the cause.",
                    "estCustAffected": "1",
                    "lastUpdateTime": "1667574384",
                    "hazardFlag": "0",
                    "latitude": "37.2844",
                    "longitude": "-120.32113"
                }
            ]
        },
        {
            "id": "5307142786",
            "regionName": "Reedley",
            "numOutages": "1",
            "customersAffected": "1",
            "latitude": "36.6029",
            "longitude": "-119.44703",
            "outages": [
                {
                    "outageNumber": "1853111",
                    "outageStartTime": "1667572617",
                    "crewEta": "1667573940",
                    "crewCurrentStatus": "PG&E is assessing the cause at the outage location.",
                    "autoEtor": "1667583900",
                    "currentEtor": "1667583900",
                    "cause": "PG&E is investigating the cause of your outage.",
                    "estCustAffected": "1",
                    "lastUpdateTime": "1667574094",
                    "hazardFlag": "1",
                    "latitude": "36.6029",
                    "longitude": "-119.44703"
                }
            ]
        },
        {
            "id": "5307142787",
            "regionName": "Rodeo",
            "numOutages": "1",
            "customersAffected": "1",
            "latitude": "38.03314",
            "longitude": "-122.26947",
            "outages": [
                {
                    "outageNumber": "1853117",
                    "outageStartTime": "1667573820",
                    "crewCurrentStatus": "PG&E has assigned a crew to assess the outage.",
                    "autoEtor": "1667589300",
                    "currentEtor": "1667589300",
                    "cause": "Unknown - PG&E will be assessing the cause.",
                    "estCustAffected": "1",
                    "lastUpdateTime": "1667573833",
                    "hazardFlag": "0",
                    "latitude": "38.03314",
                    "longitude": "-122.26947"
                }
            ]
        },
        {
            "id": "5307142791",
            "regionName": "Rutherford",
            "numOutages": "1",
            "customersAffected": "33",
            "latitude": "38.45207",
            "longitude": "-122.41749",
            "outages": [
                {
                    "outageNumber": "1853135",
                    "outageStartTime": "1667574536",
                    "crewCurrentStatus": "PG&E has assigned a crew to assess the outage.",
                    "currentEtor": "1667610000",
                    "cause": "Our preliminary determination is that your outage was caused by scheduled maintenance work.",
                    "estCustAffected": "33",
                    "lastUpdateTime": "1667574920",
                    "hazardFlag": "0",
                    "latitude": "38.45207",
                    "longitude": "-122.41749",
                    "outageDevices": [
                        {
                            "latitude": "38.43327",
                            "longitude": "-122.44261"
                        },
                        {
                            "latitude": "38.44096",
                            "longitude": "-122.43025"
                        },
                        {
                            "latitude": "38.45181",
                            "longitude": "-122.41785"
                        },
                        {
                            "latitude": "38.45269",
                            "longitude": "-122.41927"
                        },
                        {
                            "latitude": "38.44631",
                            "longitude": "-122.43465"
                        }
                    ]
                }
            ]
        },
        {
            "id": "5307142819",
            "regionName": "Saint Helena",
            "numOutages": "1",
            "customersAffected": "5",
            "latitude": "38.52272",
            "longitude": "-122.54648",
            "outages": [
                {
                    "outageNumber": "1853077",
                    "outageStartTime": "1667577600",
                    "crewCurrentStatus": "PG&E repair crew is on-site working to restore power.",
                    "currentEtor": "1667581200",
                    "cause": "Our preliminary determination is that your outage was caused by scheduled maintenance work.",
                    "estCustAffected": "5",
                    "lastUpdateTime": "1667574328",
                    "hazardFlag": "0",
                    "latitude": "38.52272",
                    "longitude": "-122.54648"
                }
            ]
        },
        {
            "id": "5307142820",
            "regionName": "San Andreas",
            "numOutages": "1",
            "customersAffected": "13",
            "latitude": "38.20612",
            "longitude": "-120.46356",
            "outages": [
                {
                    "outageNumber": "1852844",
                    "outageStartTime": "1667517240",
                    "crewCurrentStatus": "PG&E is sending a repair crew to the outage location.",
                    "currentEtor": "1667588400",
                    "cause": "PG&E is investigating the cause of your outage.",
                    "estCustAffected": "13",
                    "lastUpdateTime": "1667532754",
                    "hazardFlag": "0",
                    "latitude": "38.20612",
                    "longitude": "-120.46356",
                    "outageDevices": [
                        {
                            "latitude": "38.19711",
                            "longitude": "-120.47708"
                        },
                        {
                            "latitude": "38.20319",
                            "longitude": "-120.46471"
                        },
                        {
                            "latitude": "38.2036",
                            "longitude": "-120.46449"
                        },
                        {
                            "latitude": "38.20476",
                            "longitude": "-120.481"
                        },
                        {
                            "latitude": "38.20323",
                            "longitude": "-120.48436"
                        },
                        {
                            "latitude": "38.19779",
                            "longitude": "-120.48045"
                        }
                    ]
                }
            ]
        },
        {
            "id": "5307142821",
            "regionName": "San Ardo",
            "numOutages": "1",
            "customersAffected": "1",
            "latitude": "35.9509",
            "longitude": "-120.80959",
            "outages": [
                {
                    "outageNumber": "1853084",
                    "outageStartTime": "1667567520",
                    "crewCurrentStatus": "PG&E has assigned a crew to assess the outage.",
                    "autoEtor": "1667584800",
                    "currentEtor": "1667584800",
                    "cause": "Unknown - PG&E will be assessing the cause.",
                    "estCustAffected": "1",
                    "lastUpdateTime": "1667570295",
                    "hazardFlag": "0",
                    "latitude": "35.9509",
                    "longitude": "-120.80959"
                }
            ]
        },
        {
            "id": "5307142822",
            "regionName": "San Francisco",
            "numOutages": "1",
            "customersAffected": "7",
            "latitude": "37.76233",
            "longitude": "-122.40835",
            "outages": [
                {
                    "outageNumber": "1853144",
                    "outageStartTime": "1667574821",
                    "crewCurrentStatus": "PG&E has assigned a crew to assess the outage.",
                    "autoEtor": "1667583900",
                    "currentEtor": "1667583900",
                    "cause": "Unknown - PG&E will be assessing the cause.",
                    "estCustAffected": "7",
                    "lastUpdateTime": "1667574823",
                    "hazardFlag": "0",
                    "latitude": "37.76233",
                    "longitude": "-122.40835"
                }
            ]
        },
        {
            "id": "5307142813",
            "regionName": "San Jose",
            "numOutages": "5",
            "customersAffected": "16",
            "latitude": "37.28991",
            "longitude": "-121.8373",
            "outages": [
                {
                    "outageNumber": "1853022",
                    "outageStartTime": "1667538293",
                    "crewCurrentStatus": "PG&E is assessing the cause at the outage location.",
                    "currentEtor": "1667579400",
                    "cause": "PG&E is investigating the cause of your outage.",
                    "estCustAffected": "1",
                    "lastUpdateTime": "1667574727",
                    "hazardFlag": "0",
                    "latitude": "37.28991",
                    "longitude": "-121.8373"
                },
                {
                    "outageNumber": "1853018",
                    "outageStartTime": "1667537351",
                    "crewCurrentStatus": "PG&E has assigned a crew to assess the outage.",
                    "currentEtor": "1667584200",
                    "cause": "Unknown - PG&E will be assessing the cause.",
                    "estCustAffected": "2",
                    "lastUpdateTime": "1667559399",
                    "hazardFlag": "0",
                    "latitude": "37.18715",
                    "longitude": "-121.82035"
                },
                {
                    "outageNumber": "1853086",
                    "outageStartTime": "1667568662",
                    "crewCurrentStatus": "PG&E has assigned a crew to assess the outage.",
                    "autoEtor": "1667582100",
                    "currentEtor": "1667582100",
                    "cause": "Unknown - PG&E will be assessing the cause.",
                    "estCustAffected": "1",
                    "lastUpdateTime": "1667568667",
                    "hazardFlag": "0",
                    "latitude": "37.24094",
                    "longitude": "-121.91144"
                },
                {
                    "outageNumber": "1853110",
                    "outageStartTime": "1667572358",
                    "crewCurrentStatus": "PG&E assessment crew is en route to the outage.",
                    "autoEtor": "1667583900",
                    "currentEtor": "1667583900",
                    "cause": "Unknown - PG&E will be assessing the cause.",
                    "estCustAffected": "1",
                    "lastUpdateTime": "1667572479",
                    "hazardFlag": "2",
                    "latitude": "37.33224",
                    "longitude": "-121.91483"
                },
                {
                    "outageNumber": "1852768",
                    "outageStartTime": "1667511472",
                    "crewCurrentStatus": "PG&E is assessing the cause at the outage location.",
                    "currentEtor": "1667584200",
                    "cause": "PG&E is investigating the cause of your outage.",
                    "estCustAffected": "11",
                    "lastUpdateTime": "1667527283",
                    "hazardFlag": "0",
                    "latitude": "37.18692",
                    "longitude": "-121.81768",
                    "outageDevices": [
                        {
                            "latitude": "37.14273",
                            "longitude": "-121.83606"
                        },
                        {
                            "latitude": "37.17195",
                            "longitude": "-121.81431"
                        },
                        {
                            "latitude": "37.17413",
                            "longitude": "-121.81354"
                        },
                        {
                            "latitude": "37.17656",
                            "longitude": "-121.82027"
                        },
                        {
                            "latitude": "37.15427",
                            "longitude": "-121.84315"
                        }
                    ]
                }
            ]
        },
        {
            "id": "5307142802",
            "regionName": "San Pablo",
            "numOutages": "1",
            "customersAffected": "8",
            "latitude": "37.95593",
            "longitude": "-122.32031",
            "outages": [
                {
                    "outageNumber": "1853125",
                    "outageStartTime": "1667574027",
                    "crewCurrentStatus": "PG&E repair crew is on-site working to restore power.",
                    "currentEtor": "1667595600",
                    "cause": "Our preliminary determination is that your outage was caused by scheduled maintenance work.",
                    "estCustAffected": "8",
                    "lastUpdateTime": "1667574340",
                    "hazardFlag": "0",
                    "latitude": "37.95593",
                    "longitude": "-122.32031"
                }
            ]
        },
        {
            "id": "5307142803",
            "regionName": "Santa Maria",
            "numOutages": "3",
            "customersAffected": "108",
            "latitude": "34.90077",
            "longitude": "-120.49052",
            "outages": [
                {
                    "outageNumber": "1853096",
                    "outageStartTime": "1667574000",
                    "crewCurrentStatus": "PG&E repair crew is on-site working to restore power.",
                    "currentEtor": "1667602800",
                    "cause": "Our preliminary determination is that your outage was caused by scheduled maintenance work.",
                    "estCustAffected": "102",
                    "lastUpdateTime": "1667574637",
                    "hazardFlag": "0",
                    "latitude": "34.90077",
                    "longitude": "-120.49052",
                    "outageDevices": [
                        {
                            "latitude": "34.89784",
                            "longitude": "-120.48679"
                        },
                        {
                            "latitude": "34.89973",
                            "longitude": "-120.48677"
                        },
                        {
                            "latitude": "34.90044",
                            "longitude": "-120.48766"
                        },
                        {
                            "latitude": "34.90045",
                            "longitude": "-120.48936"
                        },
                        {
                            "latitude": "34.89807",
                            "longitude": "-120.48925"
                        }
                    ]
                },
                {
                    "outageNumber": "1853100",
                    "outageStartTime": "1667575800",
                    "crewCurrentStatus": "PG&E repair crew is on-site working to restore power.",
                    "currentEtor": "1667586600",
                    "cause": "Our preliminary determination is that your outage was caused by scheduled maintenance work.",
                    "estCustAffected": "2",
                    "lastUpdateTime": "1667571930",
                    "hazardFlag": "0",
                    "latitude": "35.02669",
                    "longitude": "-120.19688"
                },
                {
                    "outageNumber": "1853101",
                    "outageStartTime": "1667588400",
                    "crewCurrentStatus": "PG&E has assigned a crew to assess the outage.",
                    "currentEtor": "1667599200",
                    "cause": "Our preliminary determination is that your outage was caused by scheduled maintenance work.",
                    "estCustAffected": "4",
                    "lastUpdateTime": "1667571930",
                    "hazardFlag": "0",
                    "latitude": "35.01114",
                    "longitude": "-120.21132",
                    "outageDevices": [
                        {
                            "latitude": "35.01682",
                            "longitude": "-120.24223"
                        },
                        {
                            "latitude": "35.01748",
                            "longitude": "-120.22451"
                        },
                        {
                            "latitude": "35.02216",
                            "longitude": "-120.22962"
                        }
                    ]
                }
            ]
        },
        {
            "id": "5307142804",
            "regionName": "Shingle Springs",
            "numOutages": "7",
            "customersAffected": "180",
            "latitude": "38.6696",
            "longitude": "-120.95956",
            "outages": [
                {
                    "outageNumber": "1853138",
                    "outageStartTime": "1667574660",
                    "crewCurrentStatus": "PG&E repair crew is on-site working to restore power.",
                    "currentEtor": "1667590200",
                    "cause": "Our preliminary determination is that your outage was caused by scheduled maintenance work.",
                    "estCustAffected": "17",
                    "lastUpdateTime": "1667574839",
                    "hazardFlag": "0",
                    "latitude": "38.6696",
                    "longitude": "-120.95956",
                    "outageDevices": [
                        {
                            "latitude": "38.66308",
                            "longitude": "-120.96024"
                        },
                        {
                            "latitude": "38.66338",
                            "longitude": "-120.95854"
                        },
                        {
                            "latitude": "38.66381",
                            "longitude": "-120.9582"
                        },
                        {
                            "latitude": "38.66759",
                            "longitude": "-120.95821"
                        },
                        {
                            "latitude": "38.66899",
                            "longitude": "-120.95926"
                        },
                        {
                            "latitude": "38.6684",
                            "longitude": "-120.96025"
                        },
                        {
                            "latitude": "38.6667",
                            "longitude": "-120.961"
                        }
                    ]
                },
                {
                    "outageNumber": "1853153",
                    "outageStartTime": "1667574898",
                    "crewCurrentStatus": "PG&E has assigned a crew to assess the outage.",
                    "autoEtor": "1667596500",
                    "currentEtor": "1667596500",
                    "cause": "Unknown - PG&E will be assessing the cause.",
                    "estCustAffected": "1",
                    "lastUpdateTime": "1667574901",
                    "hazardFlag": "0",
                    "latitude": "38.66865",
                    "longitude": "-120.91526"
                },
                {
                    "outageNumber": "1853156",
                    "outageStartTime": "1667574909",
                    "crewCurrentStatus": "PG&E has assigned a crew to assess the outage.",
                    "autoEtor": "1667596500",
                    "currentEtor": "1667596500",
                    "cause": "Unknown - PG&E will be assessing the cause.",
                    "estCustAffected": "1",
                    "lastUpdateTime": "1667574965",
                    "hazardFlag": "0",
                    "latitude": "38.6693",
                    "longitude": "-120.91048"
                },
                {
                    "outageNumber": "1853155",
                    "outageStartTime": "1667574938",
                    "crewCurrentStatus": "PG&E has assigned a crew to assess the outage.",
                    "autoEtor": "1667596500",
                    "currentEtor": "1667596500",
                    "cause": "Unknown - PG&E will be assessing the cause.",
                    "estCustAffected": "8",
                    "lastUpdateTime": "1667574948",
                    "hazardFlag": "0",
                    "latitude": "38.66037",
                    "longitude": "-120.92297"
                },
                {
                    "outageNumber": "1853148",
                    "outageStartTime": "1667574871",
                    "crewCurrentStatus": "PG&E has assigned a crew to assess the outage.",
                    "autoEtor": "1667596500",
                    "currentEtor": "1667596500",
                    "cause": "Unknown - PG&E will be assessing the cause.",
                    "estCustAffected": "49",
                    "lastUpdateTime": "1667574966",
                    "hazardFlag": "0",
                    "latitude": "38.65383",
                    "longitude": "-120.92978",
                    "outageDevices": [
                        {
                            "latitude": "38.64714",
                            "longitude": "-120.93339"
                        },
                        {
                            "latitude": "38.64745",
                            "longitude": "-120.93021"
                        },
                        {
                            "latitude": "38.6529",
                            "longitude": "-120.92886"
                        },
                        {
                            "latitude": "38.65383",
                            "longitude": "-120.92983"
                        },
                        {
                            "latitude": "38.6545",
                            "longitude": "-120.93229"
                        },
                        {
                            "latitude": "38.652",
                            "longitude": "-120.93705"
                        }
                    ]
                },
                {
                    "outageNumber": "1853149",
                    "outageStartTime": "1667574878",
                    "crewCurrentStatus": "PG&E has assigned a crew to assess the outage.",
                    "autoEtor": "1667596500",
                    "currentEtor": "1667596500",
                    "cause": "Unknown - PG&E will be assessing the cause.",
                    "estCustAffected": "1",
                    "lastUpdateTime": "1667574883",
                    "hazardFlag": "0",
                    "latitude": "38.63016",
                    "longitude": "-120.91897"
                }
            ]
        },
        {
            "id": "5307142807",
            "regionName": "Shingletown",
            "numOutages": "1",
            "customersAffected": "94",
            "latitude": "40.44989",
            "longitude": "-121.88272",
            "outages": [
                {
                    "outageNumber": "1853120",
                    "outageStartTime": "1667574060",
                    "crewCurrentStatus": "PG&E repair crew is on-site working to restore power.",
                    "currentEtor": "1667602800",
                    "cause": "Our preliminary determination is that your outage was caused by scheduled maintenance work.",
                    "estCustAffected": "94",
                    "lastUpdateTime": "1667574812",
                    "hazardFlag": "0",
                    "latitude": "40.44989",
                    "longitude": "-121.88272",
                    "outageDevices": [
                        {
                            "latitude": "40.39397",
                            "longitude": "-121.96423"
                        },
                        {
                            "latitude": "40.41181",
                            "longitude": "-121.93386"
                        },
                        {
                            "latitude": "40.4498",
                            "longitude": "-121.88353"
                        },
                        {
                            "latitude": "40.4648",
                            "longitude": "-121.87716"
                        },
                        {
                            "latitude": "40.47233",
                            "longitude": "-121.87782"
                        },
                        {
                            "latitude": "40.47229",
                            "longitude": "-121.88329"
                        },
                        {
                            "latitude": "40.44372",
                            "longitude": "-121.99235"
                        },
                        {
                            "latitude": "40.43779",
                            "longitude": "-121.99704"
                        },
                        {
                            "latitude": "40.43164",
                            "longitude": "-122.00186"
                        },
                        {
                            "latitude": "40.40517",
                            "longitude": "-121.99047"
                        }
                    ]
                }
            ]
        },
        {
            "id": "5307142797",
            "regionName": "Smartsville",
            "numOutages": "1",
            "customersAffected": "1",
            "latitude": "39.18802",
            "longitude": "-121.24483",
            "outages": [
                {
                    "outageNumber": "1853119",
                    "outageStartTime": "1667574120",
                    "crewCurrentStatus": "PG&E repair crew is on-site working to restore power.",
                    "currentEtor": "1667602800",
                    "cause": "Our preliminary determination is that your outage was caused by scheduled maintenance work.",
                    "estCustAffected": "1",
                    "lastUpdateTime": "1667574285",
                    "hazardFlag": "0",
                    "latitude": "39.18802",
                    "longitude": "-121.24483"
                }
            ]
        },
        {
            "id": "5307142779",
            "regionName": "Stockton",
            "numOutages": "2",
            "customersAffected": "18",
            "latitude": "37.97422",
            "longitude": "-121.272",
            "outages": [
                {
                    "outageNumber": "1853123",
                    "outageStartTime": "1667574001",
                    "crewCurrentStatus": "PG&E repair crew is on-site working to restore power.",
                    "currentEtor": "1667601000",
                    "cause": "Our preliminary determination is that your outage was caused by scheduled maintenance work.",
                    "estCustAffected": "17",
                    "lastUpdateTime": "1667574321",
                    "hazardFlag": "0",
                    "latitude": "37.97422",
                    "longitude": "-121.272"
                },
                {
                    "outageNumber": "1853104",
                    "outageStartTime": "1667571838",
                    "crewCurrentStatus": "PG&E is assessing the cause at the outage location.",
                    "autoEtor": "1667586600",
                    "currentEtor": "1667586600",
                    "cause": "PG&E is investigating the cause of your outage.",
                    "estCustAffected": "1",
                    "lastUpdateTime": "1667574921",
                    "hazardFlag": "1",
                    "latitude": "38.00768",
                    "longitude": "-121.23812"
                }
            ]
        },
        {
            "id": "5307142808",
            "regionName": "Tomales",
            "numOutages": "1",
            "customersAffected": "1",
            "latitude": "38.24699",
            "longitude": "-122.90487",
            "outages": [
                {
                    "outageNumber": "1853145",
                    "outageStartTime": "1667574840",
                    "crewCurrentStatus": "PG&E has assigned a crew to assess the outage.",
                    "autoEtor": "1667586600",
                    "currentEtor": "1667586600",
                    "cause": "Unknown - PG&E will be assessing the cause.",
                    "estCustAffected": "1",
                    "lastUpdateTime": "1667574844",
                    "hazardFlag": "0",
                    "latitude": "38.24699",
                    "longitude": "-122.90487"
                }
            ]
        },
        {
            "id": "5307142788",
            "regionName": "Tracy",
            "numOutages": "1",
            "customersAffected": "13",
            "latitude": "37.73267",
            "longitude": "-121.42449",
            "outages": [
                {
                    "outageNumber": "1853089",
                    "outageStartTime": "1667570040",
                    "crewCurrentStatus": "PG&E has assigned a crew to assess the outage.",
                    "autoEtor": "1667583000",
                    "currentEtor": "1667583000",
                    "cause": "Unknown - PG&E will be assessing the cause.",
                    "estCustAffected": "13",
                    "lastUpdateTime": "1667574684",
                    "hazardFlag": "1",
                    "latitude": "37.73267",
                    "longitude": "-121.42449"
                }
            ]
        }
    ],
    "isSuccess": true
}
